iglo/__init__.py
iglo/helpers.py
iglo/lamp.py
iglo-1.2.7.dist-info/DESCRIPTION.rst
iglo-1.2.7.dist-info/METADATA
iglo-1.2.7.dist-info/RECORD
iglo-1.2.7.dist-info/WHEEL
iglo-1.2.7.dist-info/metadata.json
iglo-1.2.7.dist-info/top_level.txt
iglo-1.2.7.dist-info/zip-safe
