Metadata-Version: 1.0
Name: iglo
Version: 1.2.7
Summary: Control iGlo based RGB lights
Home-page: http://github.com/jesserockz/python-iglo
Author: Jesse Hills
Author-email: UNKNOWN
License: MIT
Platform: UNKNOWN
